md_plot/__init__.py
md_plot/load_examples.py
md_plot/md_plot.py
md_plot/examples/BimodalArtificial.gz.pkl
md_plot/examples/MTY_Clipped.gz.pkl
md_plot/examples/MuncipalIncomeTaxYield_IncomeTaxShare.gz.pkl
md_plot/examples/SampleLogInome.gz.pkl
md_plot/examples/SkewedDistribution.gz.pkl
md_plot/examples/SkewedDistributionLongTable.gz.pkl
md_plot/examples/StocksData2018Q1.gz.pkl
md_plot/examples/UniformSample.gz.pkl
md_plot/helper/__init__.py
md_plot/helper/bimodal.py
md_plot/helper/optimal_no_bins.py
md_plot/helper/pareto_density_estimation.py
md_plot/helper/pareto_radius.py
md_plot/helper/pretty.py
md_plot/helper/robust_normalization.py
md_plot/helper/signed_log.py
md_plot/helper/stat_pde_density.py
md_plot/unidip/__init__.py
md_plot/unidip/dip.py
md_plot/unidip/unidip.py
md_plot-0.2.0.dist-info/LICENSE.txt
md_plot-0.2.0.dist-info/METADATA
md_plot-0.2.0.dist-info/WHEEL
md_plot-0.2.0.dist-info/top_level.txt
md_plot-0.2.0.dist-info/RECORD
