Metadata-Version: 2.1
Name: md-plot
Version: 0.2.0
Summary: Draws a mirrored density plot for each input column
Download-URL: https://github.com/TinoGehlert/md_plot/archive/v0.2.0.tar.gz
Author: TinoGehlert
Author-email: tinogehlert@aol.com
License: GNU General Public License v3 (GPLv3)
Project-URL: R-Version, https://cran.r-project.org/web/packages/DataVisualizations/index.html
Project-URL: Source, https://github.com/TinoGehlert/md_plot
Project-URL: Docs, https://md-plot.readthedocs.io
Keywords: data_science violin density_plot
Classifier: Development Status :: 4 - Beta
Classifier: Intended Audience :: Science/Research
Classifier: License :: OSI Approved :: GNU General Public License v3 (GPLv3)
Classifier: Operating System :: OS Independent
Classifier: Programming Language :: Python :: 3.6
Classifier: Programming Language :: Python :: 3.7
Classifier: Topic :: Scientific/Engineering
License-File: LICENSE.txt
Requires-Dist: pandas (>=0.24.2)
Requires-Dist: numpy (>=1.16)
Requires-Dist: scipy (>=1.1.0)
Requires-Dist: matplotlib (>=3.1.0)
Requires-Dist: plotnine (>=0.5.1)
